myproj/__init__.py
myproj/__main__.py
myproj/core/__init__.py
myproj/core/math_ops.py
myproj/core/string_ops.py
myproj/utils/__init__.py
myproj/utils/helpers.py
myproj/version.py
nishant_project-0.1.7.dist-info/METADATA
nishant_project-0.1.7.dist-info/WHEEL
nishant_project-0.1.7.dist-info/licenses/LICENSE
nishant_project-0.1.7.dist-info/RECORD
