Metadata-Version: 2.4
Name: nishant-project
Version: 0.1.7
Summary: A reusable utility library
License-Expression: MIT
License-File: LICENSE
Author: Nishant Badhautiya
Author-email: nishantbadhautiya100@gmail.com
Requires-Python: >=3.11
Classifier: Programming Language :: Python :: 3
Classifier: Programming Language :: Python :: 3.11
Classifier: Programming Language :: Python :: 3.12
Classifier: Programming Language :: Python :: 3.13
Classifier: Programming Language :: Python :: 3.14
Requires-Dist: python-dotenv (>=1.2.1,<2.0.0)
Requires-Dist: requests (>=2.32.5,<3.0.0)
